LICENSE
MANIFEST.in
README.md
setup.py
django_mashup.egg-info/PKG-INFO
django_mashup.egg-info/SOURCES.txt
django_mashup.egg-info/dependency_links.txt
django_mashup.egg-info/requires.txt
django_mashup.egg-info/top_level.txt
mashup/__init__.py
mashup/views.py