Metadata-Version: 1.1
Name: django-mashup
Version: 0.7.1
Summary: Combine multiple views, strings of HTML, and/or ajax loaded urls into a single view.
Home-page: http://www.sigmaeducation.com/
Author: Sigma Education
Author-email: dev@sigmaeducation.com
License: GNU General Public License v3 (GPLv3)
Platform: UNKNOWN
Classifier: Development Status :: 4 - Beta
Classifier: Environment :: Web Environment
Classifier: Framework :: Django
Classifier: Intended Audience :: Developers
Classifier: License :: OSI Approved :: GNU General Public License v3 (GPLv3)
Classifier: Operating System :: OS Independent
Classifier: Programming Language :: Python
Classifier: Programming Language :: Python :: 3.4
Classifier: Topic :: Internet :: WWW/HTTP
Classifier: Topic :: Internet :: WWW/HTTP :: Dynamic Content
